qutest.py
qutest-8.1.0.dist-info/METADATA
qutest-8.1.0.dist-info/WHEEL
qutest-8.1.0.dist-info/entry_points.txt
qutest-8.1.0.dist-info/top_level.txt
qutest-8.1.0.dist-info/RECORD
